logtailtool/__init__.py
logtailtool/logtailtool.py
logtailtool-1.0.2.dist-info/LICENSE
logtailtool-1.0.2.dist-info/METADATA
logtailtool-1.0.2.dist-info/WHEEL
logtailtool-1.0.2.dist-info/top_level.txt
logtailtool-1.0.2.dist-info/RECORD
